<export>
  <head>
    <meta name="class" value="Press Tap"/>
    <meta name="userID" value="1"/>
    </head>
  <datas>
    <data id="680" xNorm="0.655422288855572" yNorm="0.0915119363395226" t="0"/>
    <data id="680" xNorm="0.655422288855572" yNorm="0.0915119363395226" t="9"/>
    <data id="680" xNorm="0.655422288855572" yNorm="0.0915119363395226" t="19"/>
    <data id="680" xNorm="0.655422288855572" yNorm="0.0915119363395226" t="29"/>
    <data id="680" xNorm="0.655422288855572" yNorm="0.0915119363395226" t="39"/>
    <data id="680" xNorm="0.655422288855572" yNorm="0.0915119363395226" t="49"/>
    <data id="680" xNorm="0.655422288855572" yNorm="0.0915119363395226" t="60"/>
    <data id="680" xNorm="0.655422288855572" yNorm="0.0915119363395226" t="70"/>
    <data id="680" xNorm="0.655422288855572" yNorm="0.0915119363395226" t="79"/>
    <data id="680" xNorm="0.655422288855572" yNorm="0.0915119363395226" t="91"/>
    <data id="680" xNorm="0.655422288855572" yNorm="0.0915119363395226" t="100"/>
    <data id="680" xNorm="0.655422288855572" yNorm="0.0915119363395226" t="110"/>
    <data id="680" xNorm="0.655422288855572" yNorm="0.0915119363395226" t="120"/>
    <data id="680" xNorm="0.655422288855572" yNorm="0.0915119363395226" t="130"/>
    <data id="680" xNorm="0.655422288855572" yNorm="0.0915119363395226" t="140"/>
    <data id="680" xNorm="0.655422288855572" yNorm="0.0915119363395226" t="150"/>
    <data id="680" xNorm="0.655422288855572" yNorm="0.0915119363395226" t="160"/>
    <data id="680" xNorm="0.655422288855572" yNorm="0.0915119363395226" t="170"/>
    <data id="680" xNorm="0.655422288855572" yNorm="0.0915119363395226" t="181"/>
    <data id="680" xNorm="0.655422288855572" yNorm="0.0915119363395226" t="191"/>
    <data id="680" xNorm="0.655422288855572" yNorm="0.0915119363395226" t="200"/>
    <data id="680" xNorm="0.655172413793103" yNorm="0.0915119363395226" t="211"/>
    <data id="681" xNorm="0.661419290354823" yNorm="0.281167108753316" t="220"/>
    <data id="680" xNorm="0.654922538730635" yNorm="0.0915119363395226" t="220"/>
    <data id="680" xNorm="0.654922538730635" yNorm="0.0915119363395226" t="232"/>
    <data id="681" xNorm="0.661419290354823" yNorm="0.281167108753316" t="232"/>
    <data id="680" xNorm="0.654922538730635" yNorm="0.0915119363395226" t="242"/>
    <data id="681" xNorm="0.661419290354823" yNorm="0.281167108753316" t="242"/>
    <data id="680" xNorm="0.654922538730635" yNorm="0.0915119363395226" t="251"/>
    <data id="681" xNorm="0.661419290354823" yNorm="0.281167108753316" t="251"/>
    <data id="680" xNorm="0.654922538730635" yNorm="0.0915119363395226" t="262"/>
    <data id="681" xNorm="0.661419290354823" yNorm="0.281167108753316" t="262"/>
    <data id="680" xNorm="0.654922538730635" yNorm="0.0915119363395226" t="271"/>
    <data id="681" xNorm="0.661419290354823" yNorm="0.281167108753316" t="271"/>
    <data id="680" xNorm="0.654922538730635" yNorm="0.0915119363395226" t="281"/>
    <data id="681" xNorm="0.661419290354823" yNorm="0.281167108753316" t="281"/>
    <data id="680" xNorm="0.654922538730635" yNorm="0.0915119363395226" t="292"/>
    <data id="681" xNorm="0.661419290354823" yNorm="0.281167108753316" t="292"/>
    <data id="680" xNorm="0.654922538730635" yNorm="0.0915119363395226" t="301"/>
    <data id="681" xNorm="0.661419290354823" yNorm="0.281167108753316" t="301"/>
    <data id="680" xNorm="0.654922538730635" yNorm="0.0915119363395226" t="321"/>
    <data id="681" xNorm="0.661419290354823" yNorm="0.281167108753316" t="321"/>
    <data id="680" xNorm="0.654922538730635" yNorm="0.0915119363395226" t="331"/>
    <data id="680" xNorm="0.654922538730635" yNorm="0.0915119363395226" t="341"/>
    <data id="680" xNorm="0.654922538730635" yNorm="0.0915119363395226" t="352"/>
    <data id="680" xNorm="0.654922538730635" yNorm="0.0915119363395226" t="431"/>
  </datas>
</export>
