<export>

<head>
<meta name="class" value="Press Scale"/>
<meta name="userID" value="20"/>
</head>
<datas>
<data id="41" xNorm="0.6209536852589642" yNorm="0.7765269053129346" t="0"/>
<data id="41" xNorm="0.6209536852589642" yNorm="0.7765269053129346" t="31"/>
<data id="41" xNorm="0.6209536852589642" yNorm="0.7765269053129346" t="31"/>
<data id="41" xNorm="0.6209536852589642" yNorm="0.7765269053129346" t="62"/>
<data id="41" xNorm="0.6209536852589642" yNorm="0.7765269053129346" t="62"/>
<data id="41" xNorm="0.6209536852589642" yNorm="0.7765269053129346" t="94"/>
<data id="41" xNorm="0.6209536852589642" yNorm="0.7765269053129346" t="94"/>
<data id="41" xNorm="0.6209536852589642" yNorm="0.7765269053129346" t="187"/>
<data id="41" xNorm="0.6212130644090319" yNorm="0.7770278420646611" t="203"/>
<data id="41" xNorm="0.6212130644090319" yNorm="0.7770278420646611" t="218"/>
<data id="41" xNorm="0.6214724435590956" yNorm="0.7775287788163876" t="234"/>
<data id="41" xNorm="0.6214724435590956" yNorm="0.7775287788163876" t="250"/>
<data id="41" xNorm="0.6214724435590956" yNorm="0.7775287788163876" t="265"/>
<data id="41" xNorm="0.6214724435590956" yNorm="0.7775287788163876" t="281"/>
<data id="41" xNorm="0.6214724435590956" yNorm="0.7775287788163876" t="281"/>
<data id="41" xNorm="0.6214724435590956" yNorm="0.7775287788163876" t="312"/>
<data id="41" xNorm="0.6214724435590956" yNorm="0.7775287788163876" t="312"/>
<data id="41" xNorm="0.6214724435590956" yNorm="0.7775287788163876" t="312"/>
<data id="42" xNorm="0.6196567895086336" yNorm="0.5781559516295469" t="312"/>
<data id="41" xNorm="0.6217318227091634" yNorm="0.7780297155681143" t="328"/>
<data id="42" xNorm="0.6196567895086336" yNorm="0.5781559516295469" t="328"/>
<data id="41" xNorm="0.6217318227091634" yNorm="0.7780297155681143" t="328"/>
<data id="42" xNorm="0.6196567895086336" yNorm="0.5781559516295469" t="328"/>
<data id="41" xNorm="0.6217318227091634" yNorm="0.7780297155681143" t="328"/>
<data id="42" xNorm="0.6196567895086336" yNorm="0.5781559516295469" t="328"/>
<data id="41" xNorm="0.6219912018592312" yNorm="0.7780297155681143" t="328"/>
<data id="42" xNorm="0.6196567895086336" yNorm="0.5781559516295469" t="328"/>
<data id="41" xNorm="0.6219912018592312" yNorm="0.7780297155681143" t="343"/>
<data id="42" xNorm="0.6196567895086336" yNorm="0.5781559516295469" t="343"/>
<data id="41" xNorm="0.6219912018592312" yNorm="0.7780297155681143" t="343"/>
<data id="42" xNorm="0.6196567895086336" yNorm="0.5781559516295469" t="343"/>
<data id="41" xNorm="0.6219912018592312" yNorm="0.7780297155681143" t="343"/>
<data id="42" xNorm="0.6196567895086336" yNorm="0.5781559516295469" t="343"/>
<data id="41" xNorm="0.6222505810092949" yNorm="0.7780297155681143" t="343"/>
<data id="42" xNorm="0.6196567895086336" yNorm="0.5781559516295469" t="343"/>
<data id="41" xNorm="0.6222505810092949" yNorm="0.7780297155681143" t="359"/>
<data id="42" xNorm="0.6193974103585658" yNorm="0.5771540781260938" t="359"/>
<data id="41" xNorm="0.6222505810092949" yNorm="0.7780297155681143" t="359"/>
<data id="42" xNorm="0.6193974103585658" yNorm="0.5771540781260938" t="359"/>
<data id="41" xNorm="0.6222505810092949" yNorm="0.7780297155681143" t="359"/>
<data id="42" xNorm="0.6191380312084981" yNorm="0.5756512678709182" t="359"/>
<data id="41" xNorm="0.6222505810092949" yNorm="0.7780297155681143" t="359"/>
<data id="42" xNorm="0.6191380312084981" yNorm="0.5756512678709182" t="359"/>
<data id="41" xNorm="0.6222505810092949" yNorm="0.7780297155681143" t="359"/>
<data id="42" xNorm="0.6188786520584344" yNorm="0.5726456473605632" t="359"/>
<data id="41" xNorm="0.6222505810092949" yNorm="0.7780297155681143" t="375"/>
<data id="42" xNorm="0.6188786520584344" yNorm="0.5726456473605632" t="375"/>
<data id="41" xNorm="0.6222505810092949" yNorm="0.7780297155681143" t="375"/>
<data id="42" xNorm="0.6188786520584344" yNorm="0.5726456473605632" t="375"/>
<data id="41" xNorm="0.6225099601593626" yNorm="0.7780297155681143" t="375"/>
<data id="42" xNorm="0.6188786520584344" yNorm="0.5726456473605632" t="375"/>
<data id="41" xNorm="0.6225099601593626" yNorm="0.7780297155681143" t="390"/>
<data id="42" xNorm="0.6183598937582988" yNorm="0.5671353430915794" t="390"/>
<data id="41" xNorm="0.6225099601593626" yNorm="0.7780297155681143" t="390"/>
<data id="42" xNorm="0.6183598937582988" yNorm="0.5671353430915794" t="390"/>
<data id="41" xNorm="0.6225099601593626" yNorm="0.7780297155681143" t="390"/>
<data id="42" xNorm="0.6178411354581674" yNorm="0.5586194183122448" t="390"/>
<data id="41" xNorm="0.6225099601593626" yNorm="0.7780297155681143" t="390"/>
<data id="42" xNorm="0.6178411354581674" yNorm="0.5586194183122448" t="390"/>
<data id="41" xNorm="0.6225099601593626" yNorm="0.7780297155681143" t="406"/>
<data id="42" xNorm="0.6178411354581674" yNorm="0.5586194183122448" t="406"/>
<data id="41" xNorm="0.6225099601593626" yNorm="0.7780297155681143" t="406"/>
<data id="42" xNorm="0.6178411354581674" yNorm="0.5586194183122448" t="406"/>
<data id="41" xNorm="0.6225099601593626" yNorm="0.7780297155681143" t="406"/>
<data id="42" xNorm="0.6175817563080996" yNorm="0.5501034935329061" t="406"/>
<data id="41" xNorm="0.6225099601593626" yNorm="0.7780297155681143" t="406"/>
<data id="42" xNorm="0.6175817563080996" yNorm="0.5501034935329061" t="406"/>
<data id="41" xNorm="0.6225099601593626" yNorm="0.7780297155681143" t="422"/>
<data id="42" xNorm="0.6170629980079682" yNorm="0.5415875687535673" t="422"/>
<data id="41" xNorm="0.6225099601593626" yNorm="0.7780297155681143" t="422"/>
<data id="42" xNorm="0.6170629980079682" yNorm="0.5415875687535673" t="422"/>
<data id="41" xNorm="0.6225099601593626" yNorm="0.7780297155681143" t="422"/>
<data id="42" xNorm="0.6165442397078368" yNorm="0.5310678969673305" t="422"/>
<data id="41" xNorm="0.6225099601593626" yNorm="0.7780297155681143" t="422"/>
<data id="42" xNorm="0.6165442397078368" yNorm="0.5310678969673305" t="422"/>
<data id="41" xNorm="0.6225099601593626" yNorm="0.7780297155681143" t="437"/>
<data id="42" xNorm="0.6165442397078368" yNorm="0.5310678969673305" t="437"/>
<data id="41" xNorm="0.6225099601593626" yNorm="0.7780297155681143" t="437"/>
<data id="42" xNorm="0.6165442397078368" yNorm="0.5310678969673305" t="437"/>
<data id="41" xNorm="0.6225099601593626" yNorm="0.7780297155681143" t="437"/>
<data id="42" xNorm="0.6168036188579005" yNorm="0.5225519721879918" t="437"/>
<data id="41" xNorm="0.6225099601593626" yNorm="0.7780297155681143" t="437"/>
<data id="42" xNorm="0.6168036188579005" yNorm="0.5225519721879918" t="437"/>
<data id="41" xNorm="0.6225099601593626" yNorm="0.7780297155681143" t="437"/>
<data id="42" xNorm="0.6170629980079682" yNorm="0.5145369841603795" t="437"/>
<data id="41" xNorm="0.6225099601593626" yNorm="0.7780297155681143" t="437"/>
<data id="42" xNorm="0.6170629980079682" yNorm="0.5145369841603795" t="437"/>
<data id="41" xNorm="0.6225099601593626" yNorm="0.7780297155681143" t="453"/>
<data id="42" xNorm="0.6170629980079682" yNorm="0.5055201226293182" t="453"/>
<data id="41" xNorm="0.6227693393094303" yNorm="0.7780297155681143" t="469"/>
<data id="42" xNorm="0.6170629980079682" yNorm="0.5055201226293182" t="469"/>
<data id="41" xNorm="0.6227693393094303" yNorm="0.7780297155681143" t="469"/>
<data id="42" xNorm="0.6170629980079682" yNorm="0.5055201226293182" t="469"/>
<data id="41" xNorm="0.6227693393094303" yNorm="0.7780297155681143" t="469"/>
<data id="42" xNorm="0.6170629980079682" yNorm="0.5055201226293182" t="469"/>
<data id="41" xNorm="0.6227693393094303" yNorm="0.7780297155681143" t="469"/>
<data id="42" xNorm="0.617322377158036" yNorm="0.49750513460170603" t="469"/>
<data id="41" xNorm="0.6227693393094303" yNorm="0.7780297155681143" t="469"/>
<data id="42" xNorm="0.617322377158036" yNorm="0.49750513460170603" t="469"/>
<data id="41" xNorm="0.6227693393094303" yNorm="0.7780297155681143" t="469"/>
<data id="42" xNorm="0.6178411354581674" yNorm="0.48999108332582036" t="469"/>
<data id="41" xNorm="0.6227693393094303" yNorm="0.7780297155681143" t="469"/>
<data id="42" xNorm="0.6178411354581674" yNorm="0.48999108332582036" t="469"/>
<data id="41" xNorm="0.6227693393094303" yNorm="0.7780297155681143" t="484"/>
<data id="42" xNorm="0.6181005146082351" yNorm="0.4824770320499347" t="484"/>
<data id="41" xNorm="0.6227693393094303" yNorm="0.7780297155681143" t="484"/>
<data id="42" xNorm="0.6181005146082351" yNorm="0.4824770320499347" t="484"/>
<data id="41" xNorm="0.6227693393094303" yNorm="0.7780297155681143" t="500"/>
<data id="42" xNorm="0.6181005146082351" yNorm="0.4824770320499347" t="500"/>
<data id="41" xNorm="0.6227693393094303" yNorm="0.7780297155681143" t="500"/>
<data id="42" xNorm="0.6181005146082351" yNorm="0.4824770320499347" t="500"/>
<data id="41" xNorm="0.6227693393094303" yNorm="0.7780297155681143" t="500"/>
<data id="42" xNorm="0.6181005146082351" yNorm="0.474962980774049" t="500"/>
<data id="41" xNorm="0.6227693393094303" yNorm="0.7780297155681143" t="500"/>
<data id="42" xNorm="0.6181005146082351" yNorm="0.474962980774049" t="500"/>
<data id="41" xNorm="0.6227693393094303" yNorm="0.7780297155681143" t="500"/>
<data id="42" xNorm="0.6183598937582988" yNorm="0.46744892949816325" t="500"/>
<data id="41" xNorm="0.6227693393094303" yNorm="0.7780297155681143" t="500"/>
<data id="42" xNorm="0.6183598937582988" yNorm="0.46744892949816325" t="500"/>
<data id="41" xNorm="0.6227693393094303" yNorm="0.7780297155681143" t="515"/>
<data id="42" xNorm="0.6188786520584344" yNorm="0.4599348782222776" t="515"/>
<data id="41" xNorm="0.6227693393094303" yNorm="0.7780297155681143" t="515"/>
<data id="42" xNorm="0.6188786520584344" yNorm="0.4599348782222776" t="515"/>
<data id="41" xNorm="0.6227693393094303" yNorm="0.7780297155681143" t="531"/>
<data id="42" xNorm="0.6191380312084981" yNorm="0.4524208269463918" t="531"/>
<data id="41" xNorm="0.6227693393094303" yNorm="0.7780297155681143" t="531"/>
<data id="42" xNorm="0.6191380312084981" yNorm="0.4524208269463918" t="531"/>
<data id="41" xNorm="0.6227693393094303" yNorm="0.7780297155681143" t="531"/>
<data id="42" xNorm="0.6196567895086336" yNorm="0.44290302866360004" t="531"/>
<data id="41" xNorm="0.6227693393094303" yNorm="0.7780297155681143" t="531"/>
<data id="42" xNorm="0.6196567895086336" yNorm="0.44290302866360004" t="531"/>
<data id="41" xNorm="0.6227693393094303" yNorm="0.7780297155681143" t="547"/>
<data id="42" xNorm="0.6206943061088964" yNorm="0.4338861671325388" t="547"/>
<data id="41" xNorm="0.6227693393094303" yNorm="0.7780297155681143" t="547"/>
<data id="42" xNorm="0.6206943061088964" yNorm="0.4338861671325388" t="547"/>
<data id="41" xNorm="0.6227693393094303" yNorm="0.7780297155681143" t="562"/>
<data id="42" xNorm="0.6217318227091634" yNorm="0.4233664953462979" t="562"/>
<data id="41" xNorm="0.6227693393094303" yNorm="0.7780297155681143" t="562"/>
<data id="42" xNorm="0.6217318227091634" yNorm="0.4233664953462979" t="562"/>
<data id="41" xNorm="0.6227693393094303" yNorm="0.7780297155681143" t="562"/>
<data id="42" xNorm="0.6217318227091634" yNorm="0.4233664953462979" t="562"/>
<data id="41" xNorm="0.6227693393094303" yNorm="0.7780297155681143" t="562"/>
<data id="42" xNorm="0.6217318227091634" yNorm="0.4233664953462979" t="562"/>
<data id="41" xNorm="0.6227693393094303" yNorm="0.7780297155681143" t="562"/>
<data id="42" xNorm="0.6227693393094303" yNorm="0.4123458868083306" t="562"/>
<data id="41" xNorm="0.6227693393094303" yNorm="0.7780297155681143" t="562"/>
<data id="42" xNorm="0.6227693393094303" yNorm="0.4123458868083306" t="562"/>
<data id="41" xNorm="0.6227693393094303" yNorm="0.7780297155681143" t="578"/>
<data id="42" xNorm="0.6238068559096932" yNorm="0.4023271517738163" t="578"/>
<data id="41" xNorm="0.6227693393094303" yNorm="0.7780297155681143" t="578"/>
<data id="42" xNorm="0.6238068559096932" yNorm="0.4023271517738163" t="578"/>
<data id="41" xNorm="0.6227693393094303" yNorm="0.7780297155681143" t="593"/>
<data id="42" xNorm="0.6245849933598925" yNorm="0.389302796228947" t="593"/>
<data id="41" xNorm="0.6227693393094303" yNorm="0.7780297155681143" t="593"/>
<data id="42" xNorm="0.6245849933598925" yNorm="0.389302796228947" t="593"/>
<data id="41" xNorm="0.6227693393094303" yNorm="0.7780297155681143" t="593"/>
<data id="42" xNorm="0.6245849933598925" yNorm="0.389302796228947" t="593"/>
<data id="41" xNorm="0.6227693393094303" yNorm="0.7780297155681143" t="593"/>
<data id="42" xNorm="0.6245849933598925" yNorm="0.389302796228947" t="593"/>
<data id="41" xNorm="0.6227693393094303" yNorm="0.7780297155681143" t="593"/>
<data id="42" xNorm="0.6253631308100916" yNorm="0.3787831244427061" t="593"/>
<data id="41" xNorm="0.6227693393094303" yNorm="0.7780297155681143" t="593"/>
<data id="42" xNorm="0.6253631308100916" yNorm="0.3787831244427061" t="593"/>
<data id="41" xNorm="0.6227693393094303" yNorm="0.7780297155681143" t="609"/>
<data id="42" xNorm="0.6261412682602908" yNorm="0.36525783214611307" t="609"/>
<data id="41" xNorm="0.6227693393094303" yNorm="0.7780297155681143" t="609"/>
<data id="42" xNorm="0.6261412682602908" yNorm="0.36525783214611307" t="609"/>
<data id="41" xNorm="0.6227693393094303" yNorm="0.7780297155681143" t="609"/>
<data id="42" xNorm="0.6269194057104901" yNorm="0.3552390971115988" t="609"/>
<data id="41" xNorm="0.6227693393094303" yNorm="0.7780297155681143" t="609"/>
<data id="42" xNorm="0.6269194057104901" yNorm="0.3552390971115988" t="609"/>
<data id="41" xNorm="0.6227693393094303" yNorm="0.7780297155681143" t="625"/>
<data id="42" xNorm="0.6269194057104901" yNorm="0.3552390971115988" t="625"/>
<data id="41" xNorm="0.6227693393094303" yNorm="0.7780297155681143" t="625"/>
<data id="42" xNorm="0.6269194057104901" yNorm="0.3552390971115988" t="625"/>
<data id="41" xNorm="0.6227693393094303" yNorm="0.7780297155681143" t="625"/>
<data id="42" xNorm="0.6274381640106256" yNorm="0.3462222355805355" t="625"/>
<data id="41" xNorm="0.6225099601593626" yNorm="0.7780297155681143" t="640"/>
<data id="42" xNorm="0.6274381640106256" yNorm="0.3462222355805355" t="640"/>
<data id="41" xNorm="0.6225099601593626" yNorm="0.7780297155681143" t="640"/>
<data id="42" xNorm="0.6279569223107571" yNorm="0.33570256379429547" t="640"/>
<data id="41" xNorm="0.6225099601593626" yNorm="0.7780297155681143" t="640"/>
<data id="42" xNorm="0.6279569223107571" yNorm="0.33570256379429547" t="640"/>
<data id="41" xNorm="0.6225099601593626" yNorm="0.7780297155681143" t="640"/>
<data id="42" xNorm="0.628994438911024" yNorm="0.327186639014958" t="640"/>
<data id="41" xNorm="0.6222505810092949" yNorm="0.7780297155681143" t="656"/>
<data id="42" xNorm="0.628994438911024" yNorm="0.327186639014958" t="656"/>
<data id="41" xNorm="0.6222505810092949" yNorm="0.7780297155681143" t="656"/>
<data id="42" xNorm="0.628994438911024" yNorm="0.327186639014958" t="656"/>
<data id="41" xNorm="0.6222505810092949" yNorm="0.7780297155681143" t="656"/>
<data id="42" xNorm="0.628994438911024" yNorm="0.327186639014958" t="656"/>
<data id="41" xNorm="0.6222505810092949" yNorm="0.7780297155681143" t="656"/>
<data id="42" xNorm="0.6300319555112869" yNorm="0.31967258773907226" t="656"/>
<data id="41" xNorm="0.6219912018592312" yNorm="0.7780297155681143" t="672"/>
<data id="42" xNorm="0.6300319555112869" yNorm="0.31967258773907226" t="672"/>
<data id="41" xNorm="0.6219912018592312" yNorm="0.7780297155681143" t="672"/>
<data id="42" xNorm="0.6313288512616216" yNorm="0.3116575997114604" t="672"/>
<data id="41" xNorm="0.6219912018592312" yNorm="0.7780297155681143" t="672"/>
<data id="42" xNorm="0.6313288512616216" yNorm="0.3116575997114604" t="672"/>
<data id="41" xNorm="0.6219912018592312" yNorm="0.7780297155681143" t="672"/>
<data id="42" xNorm="0.6336632636122193" yNorm="0.30314167493212324" t="672"/>
<data id="41" xNorm="0.6219912018592312" yNorm="0.7780297155681143" t="672"/>
<data id="42" xNorm="0.6336632636122193" yNorm="0.30314167493212324" t="672"/>
<data id="41" xNorm="0.6219912018592312" yNorm="0.7780297155681143" t="687"/>
<data id="42" xNorm="0.6336632636122193" yNorm="0.30314167493212324" t="687"/>
<data id="41" xNorm="0.6219912018592312" yNorm="0.7780297155681143" t="687"/>
<data id="42" xNorm="0.6336632636122193" yNorm="0.30314167493212324" t="687"/>
<data id="41" xNorm="0.6219912018592312" yNorm="0.7780297155681143" t="687"/>
<data id="42" xNorm="0.6352195385126176" yNorm="0.29763137066314" t="687"/>
<data id="41" xNorm="0.6217318227091634" yNorm="0.7780297155681143" t="703"/>
<data id="42" xNorm="0.6352195385126176" yNorm="0.29763137066314" t="703"/>
<data id="41" xNorm="0.6217318227091634" yNorm="0.7780297155681143" t="703"/>
<data id="42" xNorm="0.6362570551128806" yNorm="0.29162012964243145" t="703"/>
<data id="41" xNorm="0.6214724435590956" yNorm="0.7780297155681143" t="703"/>
<data id="42" xNorm="0.6362570551128806" yNorm="0.29162012964243145" t="703"/>
<data id="41" xNorm="0.6214724435590956" yNorm="0.7780297155681143" t="718"/>
<data id="42" xNorm="0.6375539508632152" yNorm="0.2851079518699967" t="718"/>
<data id="41" xNorm="0.6214724435590956" yNorm="0.7780297155681143" t="718"/>
<data id="42" xNorm="0.6375539508632152" yNorm="0.2851079518699967" t="718"/>
<data id="41" xNorm="0.6214724435590956" yNorm="0.7780297155681143" t="718"/>
<data id="42" xNorm="0.6375539508632152" yNorm="0.2851079518699967" t="718"/>
<data id="41" xNorm="0.6214724435590956" yNorm="0.7780297155681143" t="718"/>
<data id="42" xNorm="0.6385914674634782" yNorm="0.2785957740975624" t="718"/>
<data id="41" xNorm="0.6212130644090319" yNorm="0.7780297155681143" t="718"/>
<data id="42" xNorm="0.6385914674634782" yNorm="0.2785957740975624" t="718"/>
<data id="41" xNorm="0.6212130644090319" yNorm="0.7780297155681143" t="734"/>
<data id="42" xNorm="0.6393696049136773" yNorm="0.2730854698285796" t="734"/>
<data id="41" xNorm="0.6209536852589642" yNorm="0.7780297155681143" t="734"/>
<data id="42" xNorm="0.6393696049136773" yNorm="0.2730854698285796" t="734"/>
<data id="41" xNorm="0.6209536852589642" yNorm="0.7780297155681143" t="750"/>
<data id="42" xNorm="0.6401477423638765" yNorm="0.26857703906304775" t="750"/>
<data id="41" xNorm="0.6209536852589642" yNorm="0.7780297155681143" t="750"/>
<data id="42" xNorm="0.6401477423638765" yNorm="0.26857703906304775" t="750"/>
<data id="41" xNorm="0.6209536852589642" yNorm="0.7780297155681143" t="750"/>
<data id="42" xNorm="0.6401477423638765" yNorm="0.26857703906304775" t="750"/>
<data id="41" xNorm="0.6209536852589642" yNorm="0.7780297155681143" t="750"/>
<data id="42" xNorm="0.6401477423638765" yNorm="0.26857703906304775" t="750"/>
<data id="41" xNorm="0.6209536852589642" yNorm="0.7780297155681143" t="750"/>
<data id="42" xNorm="0.6409258798140757" yNorm="0.2635676715457906" t="750"/>
<data id="41" xNorm="0.6209536852589642" yNorm="0.7780297155681143" t="750"/>
<data id="42" xNorm="0.6409258798140757" yNorm="0.2635676715457906" t="750"/>
<data id="41" xNorm="0.6209536852589642" yNorm="0.7780297155681143" t="765"/>
<data id="42" xNorm="0.641704017264275" yNorm="0.25855830402853347" t="765"/>
<data id="41" xNorm="0.6209536852589642" yNorm="0.7780297155681143" t="765"/>
<data id="42" xNorm="0.641704017264275" yNorm="0.25855830402853347" t="765"/>
<data id="41" xNorm="0.6209536852589642" yNorm="0.7780297155681143" t="765"/>
<data id="42" xNorm="0.6427415338645419" yNorm="0.25455081001472735" t="765"/>
<data id="41" xNorm="0.6209536852589642" yNorm="0.7780297155681143" t="765"/>
<data id="42" xNorm="0.6427415338645419" yNorm="0.25455081001472735" t="765"/>
<data id="41" xNorm="0.6209536852589642" yNorm="0.7780297155681143" t="781"/>
<data id="42" xNorm="0.6427415338645419" yNorm="0.25455081001472735" t="781"/>
<data id="41" xNorm="0.6209536852589642" yNorm="0.7780297155681143" t="797"/>
<data id="42" xNorm="0.6427415338645419" yNorm="0.25455081001472735" t="797"/>
<data id="41" xNorm="0.6209536852589642" yNorm="0.7780297155681143" t="797"/>
<data id="42" xNorm="0.6427415338645419" yNorm="0.25455081001472735" t="797"/>
<data id="41" xNorm="0.6209536852589642" yNorm="0.7780297155681143" t="797"/>
<data id="42" xNorm="0.6427415338645419" yNorm="0.25455081001472735" t="797"/>
<data id="41" xNorm="0.6206943061088964" yNorm="0.7785306523198368" t="797"/>
<data id="41" xNorm="0.6206943061088964" yNorm="0.7785306523198368" t="812"/>
<data id="41" xNorm="0.6206943061088964" yNorm="0.7785306523198368" t="828"/>
<data id="41" xNorm="0.6206943061088964" yNorm="0.7785306523198368" t="844"/>
<data id="41" xNorm="0.6206943061088964" yNorm="0.7785306523198368" t="859"/>
<data id="41" xNorm="0.6206943061088964" yNorm="0.7785306523198368" t="875"/>
<data id="41" xNorm="0.6206943061088964" yNorm="0.7785306523198368" t="890"/>
</datas>
</export>
