<export>

<head>
<meta name="class" value="Press Double Tap"/>
<meta name="userID" value="22"/>
</head>
<datas>
<data id="18" xNorm="0.2637885956175299" yNorm="0.2264983519180869" t="0"/>
<data id="18" xNorm="0.2637885956175299" yNorm="0.2264983519180869" t="31"/>
<data id="18" xNorm="0.2637885956175299" yNorm="0.2264983519180869" t="31"/>
<data id="18" xNorm="0.2637885956175299" yNorm="0.2264983519180869" t="63"/>
<data id="18" xNorm="0.2637885956175299" yNorm="0.2264983519180869" t="63"/>
<data id="18" xNorm="0.2637885956175299" yNorm="0.2264983519180869" t="94"/>
<data id="18" xNorm="0.2637885956175299" yNorm="0.2264983519180869" t="94"/>
<data id="18" xNorm="0.2637885956175299" yNorm="0.2264983519180869" t="125"/>
<data id="18" xNorm="0.2637885956175299" yNorm="0.2264983519180869" t="125"/>
<data id="18" xNorm="0.2637885956175299" yNorm="0.2264983519180869" t="156"/>
<data id="18" xNorm="0.2637885956175299" yNorm="0.2264983519180869" t="156"/>
<data id="18" xNorm="0.2637885956175299" yNorm="0.2264983519180869" t="188"/>
<data id="18" xNorm="0.2637885956175299" yNorm="0.2264983519180869" t="203"/>
<data id="18" xNorm="0.2637885956175299" yNorm="0.2264983519180869" t="219"/>
<data id="19" xNorm="0.3556088147410359" yNorm="0.47295923376714283" t="219"/>
<data id="18" xNorm="0.2637885956175299" yNorm="0.2264983519180869" t="219"/>
<data id="19" xNorm="0.3556088147410359" yNorm="0.47295923376714283" t="219"/>
<data id="18" xNorm="0.2637885956175299" yNorm="0.2264983519180869" t="219"/>
<data id="19" xNorm="0.3556088147410359" yNorm="0.47295923376714283" t="219"/>
<data id="18" xNorm="0.2637885956175299" yNorm="0.2264983519180869" t="219"/>
<data id="19" xNorm="0.3556088147410359" yNorm="0.47295923376714283" t="219"/>
<data id="18" xNorm="0.2637885956175299" yNorm="0.2264983519180869" t="219"/>
<data id="19" xNorm="0.3556088147410359" yNorm="0.47295923376714283" t="219"/>
<data id="18" xNorm="0.2637885956175299" yNorm="0.2264983519180869" t="219"/>
<data id="19" xNorm="0.3556088147410359" yNorm="0.47295923376714283" t="219"/>
<data id="18" xNorm="0.2637885956175299" yNorm="0.2264983519180869" t="219"/>
<data id="19" xNorm="0.3556088147410359" yNorm="0.47295923376714283" t="219"/>
<data id="18" xNorm="0.2637885956175299" yNorm="0.2264983519180869" t="219"/>
<data id="19" xNorm="0.3556088147410359" yNorm="0.47295923376714283" t="219"/>
<data id="18" xNorm="0.2637885956175299" yNorm="0.2264983519180869" t="219"/>
<data id="19" xNorm="0.3556088147410359" yNorm="0.47295923376714283" t="219"/>
<data id="18" xNorm="0.2637885956175299" yNorm="0.2264983519180869" t="219"/>
<data id="19" xNorm="0.3556088147410359" yNorm="0.47295923376714283" t="219"/>
<data id="18" xNorm="0.2637885956175299" yNorm="0.2264983519180869" t="235"/>
<data id="19" xNorm="0.3556088147410359" yNorm="0.47295923376714283" t="235"/>
<data id="18" xNorm="0.2637885956175299" yNorm="0.2264983519180869" t="235"/>
<data id="19" xNorm="0.3556088147410359" yNorm="0.47295923376714283" t="235"/>
<data id="18" xNorm="0.2637885956175299" yNorm="0.2264983519180869" t="250"/>
<data id="19" xNorm="0.3556088147410359" yNorm="0.47295923376714283" t="250"/>
<data id="18" xNorm="0.2637885956175299" yNorm="0.2264983519180869" t="250"/>
<data id="19" xNorm="0.3556088147410359" yNorm="0.47295923376714283" t="250"/>
<data id="18" xNorm="0.2637885956175299" yNorm="0.2264983519180869" t="250"/>
<data id="19" xNorm="0.3556088147410359" yNorm="0.47295923376714283" t="250"/>
<data id="18" xNorm="0.2637885956175299" yNorm="0.2264983519180869" t="250"/>
<data id="19" xNorm="0.3556088147410359" yNorm="0.47295923376714283" t="250"/>
<data id="18" xNorm="0.2637885956175299" yNorm="0.2264983519180869" t="250"/>
<data id="19" xNorm="0.3556088147410359" yNorm="0.47295923376714283" t="250"/>
<data id="18" xNorm="0.2637885956175299" yNorm="0.2264983519180869" t="250"/>
<data id="19" xNorm="0.3556088147410359" yNorm="0.47396110727059587" t="250"/>
<data id="18" xNorm="0.2637885956175299" yNorm="0.2264983519180869" t="266"/>
<data id="19" xNorm="0.3556088147410359" yNorm="0.47396110727059587" t="266"/>
<data id="18" xNorm="0.2637885956175299" yNorm="0.2264983519180869" t="266"/>
<data id="19" xNorm="0.3556088147410359" yNorm="0.47396110727059587" t="266"/>
<data id="18" xNorm="0.2637885956175299" yNorm="0.2264983519180869" t="297"/>
<data id="19" xNorm="0.3556088147410359" yNorm="0.47396110727059587" t="297"/>
<data id="18" xNorm="0.2637885956175299" yNorm="0.2264983519180869" t="297"/>
<data id="19" xNorm="0.3556088147410359" yNorm="0.47396110727059587" t="297"/>
<data id="18" xNorm="0.2637885956175299" yNorm="0.2264983519180869" t="297"/>
<data id="18" xNorm="0.2637885956175299" yNorm="0.2264983519180869" t="313"/>
<data id="18" xNorm="0.2637885956175299" yNorm="0.2264983519180869" t="313"/>
<data id="18" xNorm="0.2637885956175299" yNorm="0.2264983519180869" t="344"/>
<data id="18" xNorm="0.2637885956175299" yNorm="0.2264983519180869" t="344"/>
<data id="18" xNorm="0.2637885956175299" yNorm="0.2264983519180869" t="375"/>
<data id="18" xNorm="0.26404797476759645" yNorm="0.2264983519180869" t="375"/>
<data id="18" xNorm="0.2643073539176626" yNorm="0.22699928866981264" t="406"/>
<data id="18" xNorm="0.2643073539176626" yNorm="0.22699928866981264" t="406"/>
<data id="20" xNorm="0.35690571049136777" yNorm="0.5000098183603346" t="406"/>
<data id="18" xNorm="0.2643073539176626" yNorm="0.22699928866981264" t="406"/>
<data id="20" xNorm="0.35690571049136777" yNorm="0.5000098183603346" t="406"/>
<data id="18" xNorm="0.2643073539176626" yNorm="0.22699928866981264" t="406"/>
<data id="20" xNorm="0.35690571049136777" yNorm="0.5000098183603346" t="406"/>
<data id="18" xNorm="0.2643073539176626" yNorm="0.22699928866981264" t="406"/>
<data id="20" xNorm="0.35690571049136777" yNorm="0.5000098183603346" t="406"/>
<data id="18" xNorm="0.2643073539176626" yNorm="0.22699928866981264" t="406"/>
<data id="20" xNorm="0.35690571049136777" yNorm="0.5000098183603346" t="406"/>
<data id="18" xNorm="0.2643073539176626" yNorm="0.22699928866981264" t="406"/>
<data id="20" xNorm="0.35690571049136777" yNorm="0.5000098183603346" t="406"/>
<data id="18" xNorm="0.2643073539176626" yNorm="0.22699928866981264" t="422"/>
<data id="20" xNorm="0.35690571049136777" yNorm="0.5000098183603346" t="422"/>
<data id="18" xNorm="0.2643073539176626" yNorm="0.22699928866981264" t="422"/>
<data id="20" xNorm="0.35690571049136777" yNorm="0.5000098183603346" t="422"/>
<data id="18" xNorm="0.2643073539176626" yNorm="0.22699928866981264" t="422"/>
<data id="20" xNorm="0.35690571049136777" yNorm="0.5000098183603346" t="422"/>
<data id="18" xNorm="0.2643073539176626" yNorm="0.22699928866981264" t="422"/>
<data id="20" xNorm="0.35690571049136777" yNorm="0.5000098183603346" t="422"/>
<data id="18" xNorm="0.2643073539176626" yNorm="0.22699928866981264" t="438"/>
<data id="20" xNorm="0.35690571049136777" yNorm="0.5000098183603346" t="438"/>
<data id="18" xNorm="0.2643073539176626" yNorm="0.22699928866981264" t="438"/>
<data id="20" xNorm="0.35690571049136777" yNorm="0.5000098183603346" t="438"/>
<data id="18" xNorm="0.2643073539176626" yNorm="0.22699928866981264" t="438"/>
<data id="20" xNorm="0.35690571049136777" yNorm="0.5000098183603346" t="438"/>
<data id="18" xNorm="0.2643073539176626" yNorm="0.22699928866981264" t="438"/>
<data id="20" xNorm="0.35690571049136777" yNorm="0.5000098183603346" t="438"/>
<data id="18" xNorm="0.2643073539176626" yNorm="0.22699928866981264" t="453"/>
<data id="20" xNorm="0.35690571049136777" yNorm="0.5000098183603346" t="453"/>
<data id="18" xNorm="0.2643073539176626" yNorm="0.22699928866981264" t="453"/>
<data id="20" xNorm="0.35690571049136777" yNorm="0.5000098183603346" t="453"/>
<data id="18" xNorm="0.2643073539176626" yNorm="0.22699928866981264" t="453"/>
<data id="20" xNorm="0.35690571049136777" yNorm="0.5000098183603346" t="453"/>
<data id="18" xNorm="0.2643073539176626" yNorm="0.22699928866981264" t="453"/>
<data id="20" xNorm="0.35690571049136777" yNorm="0.5000098183603346" t="453"/>
<data id="18" xNorm="0.2643073539176626" yNorm="0.22699928866981264" t="469"/>
<data id="20" xNorm="0.35690571049136777" yNorm="0.5000098183603346" t="469"/>
<data id="18" xNorm="0.2643073539176626" yNorm="0.22699928866981264" t="469"/>
<data id="20" xNorm="0.35690571049136777" yNorm="0.5000098183603346" t="469"/>
<data id="18" xNorm="0.2643073539176626" yNorm="0.22699928866981264" t="469"/>
<data id="20" xNorm="0.35690571049136777" yNorm="0.5000098183603346" t="469"/>
<data id="18" xNorm="0.2643073539176626" yNorm="0.22699928866981264" t="469"/>
<data id="20" xNorm="0.35690571049136777" yNorm="0.5000098183603346" t="469"/>
<data id="18" xNorm="0.2643073539176626" yNorm="0.22699928866981264" t="484"/>
<data id="20" xNorm="0.35690571049136777" yNorm="0.5000098183603346" t="484"/>
<data id="18" xNorm="0.2643073539176626" yNorm="0.22699928866981264" t="484"/>
<data id="20" xNorm="0.35690571049136777" yNorm="0.5000098183603346" t="484"/>
<data id="18" xNorm="0.2643073539176626" yNorm="0.22699928866981264" t="500"/>
<data id="18" xNorm="0.2643073539176626" yNorm="0.22699928866981264" t="500"/>
<data id="18" xNorm="0.2643073539176626" yNorm="0.22699928866981264" t="516"/>
<data id="18" xNorm="0.2643073539176626" yNorm="0.22699928866981264" t="532"/>
<data id="18" xNorm="0.2643073539176626" yNorm="0.22699928866981264" t="532"/>
<data id="18" xNorm="0.2643073539176626" yNorm="0.22699928866981264" t="547"/>
</datas>
</export>
