<export>
  <head>
    <meta name="class" value="Rotation"/>
    <meta name="userID" value="9"/>
    </head>
  <datas>
    <data id="2" xNorm="0.335082458770615" yNorm="0.335543766578249" t="0"/>
    <data id="2" xNorm="0.335082458770615" yNorm="0.335543766578249" t="9"/>
    <data id="3" xNorm="0.577461269365317" yNorm="0.407161803713528" t="20"/>
    <data id="2" xNorm="0.335082458770615" yNorm="0.335543766578249" t="20"/>
    <data id="2" xNorm="0.335082458770615" yNorm="0.335543766578249" t="30"/>
    <data id="3" xNorm="0.577461269365317" yNorm="0.407161803713528" t="30"/>
    <data id="2" xNorm="0.335082458770615" yNorm="0.335101679929266" t="40"/>
    <data id="3" xNorm="0.577461269365317" yNorm="0.407161803713528" t="40"/>
    <data id="2" xNorm="0.335332333833083" yNorm="0.334659593280283" t="50"/>
    <data id="3" xNorm="0.577461269365317" yNorm="0.407161803713528" t="50"/>
    <data id="2" xNorm="0.335832083958021" yNorm="0.333333333333333" t="60"/>
    <data id="3" xNorm="0.577461269365317" yNorm="0.407603890362511" t="60"/>
    <data id="2" xNorm="0.336331834082959" yNorm="0.332007073386384" t="70"/>
    <data id="3" xNorm="0.577211394302849" yNorm="0.409372236958444" t="70"/>
    <data id="2" xNorm="0.337081459270365" yNorm="0.330238726790451" t="80"/>
    <data id="3" xNorm="0.576461769115442" yNorm="0.412908930150309" t="80"/>
    <data id="2" xNorm="0.338330834582709" yNorm="0.327586206896552" t="90"/>
    <data id="3" xNorm="0.57496251874063" yNorm="0.420424403183024" t="90"/>
    <data id="2" xNorm="0.340579710144928" yNorm="0.324491600353669" t="100"/>
    <data id="3" xNorm="0.572713643178411" yNorm="0.430592396109638" t="100"/>
    <data id="2" xNorm="0.344327836081959" yNorm="0.320070733863837" t="110"/>
    <data id="3" xNorm="0.569965017491254" yNorm="0.442970822281167" t="110"/>
    <data id="2" xNorm="0.34807596201899" yNorm="0.316091954022989" t="120"/>
    <data id="3" xNorm="0.56671664167916" yNorm="0.456233421750663" t="120"/>
    <data id="2" xNorm="0.354072963518241" yNorm="0.311671087533156" t="130"/>
    <data id="3" xNorm="0.562968515742129" yNorm="0.469938107869142" t="130"/>
    <data id="2" xNorm="0.359820089955023" yNorm="0.308134394341291" t="140"/>
    <data id="3" xNorm="0.557971014492754" yNorm="0.483200707338638" t="140"/>
    <data id="2" xNorm="0.36631684157921" yNorm="0.305481874447392" t="150"/>
    <data id="3" xNorm="0.553223388305847" yNorm="0.496463306808134" t="150"/>
    <data id="2" xNorm="0.373563218390805" yNorm="0.303271441202476" t="160"/>
    <data id="3" xNorm="0.547976011994003" yNorm="0.508399646330681" t="160"/>
    <data id="2" xNorm="0.382308845577211" yNorm="0.30106100795756" t="171"/>
    <data id="3" xNorm="0.541729135432284" yNorm="0.52077807250221" t="171"/>
    <data id="2" xNorm="0.389305347326337" yNorm="0.300176834659593" t="181"/>
    <data id="3" xNorm="0.535232383808096" yNorm="0.532714412024757" t="181"/>
    <data id="2" xNorm="0.398550724637681" yNorm="0.299292661361627" t="191"/>
    <data id="3" xNorm="0.528735632183908" yNorm="0.541556145004421" t="191"/>
    <data id="2" xNorm="0.407796101949025" yNorm="0.299292661361627" t="201"/>
    <data id="3" xNorm="0.522738630684658" yNorm="0.549955791335102" t="201"/>
    <data id="2" xNorm="0.416291854072964" yNorm="0.29973474801061" t="211"/>
    <data id="3" xNorm="0.515742128935532" yNorm="0.558797524314766" t="211"/>
    <data id="2" xNorm="0.426036981509245" yNorm="0.30106100795756" t="220"/>
    <data id="3" xNorm="0.509245377311344" yNorm="0.564544650751547" t="220"/>
    <data id="2" xNorm="0.434532733633183" yNorm="0.303271441202476" t="230"/>
    <data id="3" xNorm="0.501249375312344" yNorm="0.569849690539346" t="230"/>
    <data id="2" xNorm="0.44327836081959" yNorm="0.305923961096375" t="241"/>
    <data id="3" xNorm="0.494752623688156" yNorm="0.572944297082228" t="241"/>
    <data id="2" xNorm="0.450274862568716" yNorm="0.309902740937224" t="251"/>
    <data id="3" xNorm="0.488005997001499" yNorm="0.575154730327144" t="251"/>
    <data id="2" xNorm="0.459270364817591" yNorm="0.314323607427056" t="261"/>
    <data id="3" xNorm="0.478010994502749" yNorm="0.576480990274094" t="261"/>
    <data id="2" xNorm="0.468015992003998" yNorm="0.317860300618921" t="271"/>
    <data id="3" xNorm="0.470764617691154" yNorm="0.576923076923077" t="271"/>
    <data id="2" xNorm="0.474512743628186" yNorm="0.322723253757737" t="281"/>
    <data id="3" xNorm="0.464267866066967" yNorm="0.576038903625111" t="281"/>
    <data id="2" xNorm="0.480759620189905" yNorm="0.329354553492485" t="291"/>
    <data id="3" xNorm="0.456521739130435" yNorm="0.574270557029178" t="291"/>
    <data id="2" xNorm="0.487506246876562" yNorm="0.335985853227233" t="301"/>
    <data id="3" xNorm="0.449025487256372" yNorm="0.570733863837312" t="301"/>
    <data id="2" xNorm="0.492753623188406" yNorm="0.342175066312997" t="311"/>
    <data id="3" xNorm="0.44127936031984" yNorm="0.564986737400531" t="311"/>
    <data id="2" xNorm="0.499000499750125" yNorm="0.350574712643678" t="321"/>
    <data id="3" xNorm="0.43528235882059" yNorm="0.559239610963749" t="321"/>
    <data id="2" xNorm="0.503748125937031" yNorm="0.357648099027409" t="331"/>
    <data id="3" xNorm="0.428785607196402" yNorm="0.553492484526967" t="331"/>
    <data id="2" xNorm="0.507496251874063" yNorm="0.364279398762157" t="341"/>
    <data id="3" xNorm="0.42303848075962" yNorm="0.54553492484527" t="341"/>
    <data id="2" xNorm="0.510994502748626" yNorm="0.372679045092838" t="352"/>
    <data id="3" xNorm="0.417291354322839" yNorm="0.537577365163572" t="352"/>
    <data id="2" xNorm="0.513993003498251" yNorm="0.380636604774536" t="362"/>
    <data id="3" xNorm="0.411794102948526" yNorm="0.530061892130858" t="362"/>
    <data id="2" xNorm="0.516491754122939" yNorm="0.387267904509284" t="372"/>
    <data id="3" xNorm="0.407296351824088" yNorm="0.521662245800177" t="372"/>
    <data id="2" xNorm="0.518990504747626" yNorm="0.395225464190981" t="382"/>
    <data id="3" xNorm="0.403798100949525" yNorm="0.514146772767462" t="382"/>
    <data id="2" xNorm="0.520739630184908" yNorm="0.402298850574713" t="392"/>
    <data id="3" xNorm="0.4007996001999" yNorm="0.508399646330681" t="392"/>
    <data id="2" xNorm="0.521989005497251" yNorm="0.407603890362511" t="401"/>
    <data id="3" xNorm="0.397301349325337" yNorm="0.500884173297966" t="401"/>
    <data id="2" xNorm="0.523238380809595" yNorm="0.412024756852343" t="412"/>
    <data id="3" xNorm="0.39480259870065" yNorm="0.494694960212202" t="412"/>
    <data id="2" xNorm="0.523988005997001" yNorm="0.415561450044209" t="422"/>
    <data id="3" xNorm="0.3928035982009" yNorm="0.489832007073386" t="422"/>
    <data id="2" xNorm="0.524737631184408" yNorm="0.418656056587091" t="432"/>
    <data id="3" xNorm="0.391304347826087" yNorm="0.486295313881521" t="432"/>
    <data id="2" xNorm="0.525237381309345" yNorm="0.42130857648099" t="442"/>
    <data id="3" xNorm="0.390054972513743" yNorm="0.483200707338638" t="442"/>
    <data id="2" xNorm="0.525487256371814" yNorm="0.423961096374889" t="452"/>
    <data id="3" xNorm="0.389055472263868" yNorm="0.480548187444739" t="452"/>
    <data id="2" xNorm="0.525737131434283" yNorm="0.426171529619805" t="462"/>
    <data id="3" xNorm="0.388305847076462" yNorm="0.478337754199823" t="462"/>
    <data id="2" xNorm="0.525987006496752" yNorm="0.427939876215738" t="472"/>
    <data id="3" xNorm="0.387806096951524" yNorm="0.476127320954907" t="472"/>
    <data id="2" xNorm="0.525987006496752" yNorm="0.429266136162688" t="482"/>
    <data id="3" xNorm="0.387306346826587" yNorm="0.474358974358974" t="482"/>
    <data id="2" xNorm="0.525987006496752" yNorm="0.430150309460654" t="492"/>
    <data id="3" xNorm="0.387056471764118" yNorm="0.472590627763042" t="492"/>
    <data id="2" xNorm="0.525987006496752" yNorm="0.431034482758621" t="502"/>
    <data id="3" xNorm="0.386806596701649" yNorm="0.471264367816092" t="502"/>
    <data id="2" xNorm="0.525987006496752" yNorm="0.431476569407604" t="512"/>
    <data id="3" xNorm="0.38655672163918" yNorm="0.469938107869142" t="512"/>
    <data id="2" xNorm="0.525987006496752" yNorm="0.431918656056587" t="522"/>
    <data id="3" xNorm="0.386306846576712" yNorm="0.468611847922193" t="522"/>
    <data id="2" xNorm="0.525987006496752" yNorm="0.43236074270557" t="533"/>
    <data id="3" xNorm="0.386056971514243" yNorm="0.467727674624226" t="533"/>
    <data id="2" xNorm="0.525987006496752" yNorm="0.432802829354554" t="543"/>
    <data id="3" xNorm="0.386056971514243" yNorm="0.46684350132626" t="543"/>
    <data id="2" xNorm="0.525987006496752" yNorm="0.433244916003537" t="553"/>
    <data id="3" xNorm="0.386056971514243" yNorm="0.465959328028294" t="553"/>
    <data id="2" xNorm="0.525987006496752" yNorm="0.43368700265252" t="563"/>
    <data id="3" xNorm="0.386056971514243" yNorm="0.46551724137931" t="563"/>
    <data id="2" xNorm="0.525987006496752" yNorm="0.43368700265252" t="573"/>
    <data id="3" xNorm="0.386056971514243" yNorm="0.465075154730327" t="573"/>
    <data id="2" xNorm="0.525987006496752" yNorm="0.43368700265252" t="583"/>
    <data id="3" xNorm="0.386056971514243" yNorm="0.464633068081344" t="583"/>
    <data id="2" xNorm="0.525987006496752" yNorm="0.43368700265252" t="592"/>
    <data id="3" xNorm="0.386056971514243" yNorm="0.464190981432361" t="592"/>
    <data id="2" xNorm="0.525987006496752" yNorm="0.43368700265252" t="603"/>
    <data id="3" xNorm="0.386056971514243" yNorm="0.463748894783378" t="603"/>
    <data id="2" xNorm="0.525987006496752" yNorm="0.43368700265252" t="613"/>
    <data id="3" xNorm="0.386056971514243" yNorm="0.463306808134394" t="613"/>
    <data id="2" xNorm="0.525987006496752" yNorm="0.43368700265252" t="623"/>
    <data id="3" xNorm="0.386056971514243" yNorm="0.462864721485411" t="623"/>
    <data id="2" xNorm="0.525987006496752" yNorm="0.434129089301503" t="633"/>
    <data id="3" xNorm="0.386056971514243" yNorm="0.462864721485411" t="633"/>
    <data id="2" xNorm="0.525987006496752" yNorm="0.434571175950486" t="653"/>
    <data id="3" xNorm="0.386056971514243" yNorm="0.462864721485411" t="653"/>
    <data id="2" xNorm="0.525987006496752" yNorm="0.435013262599469" t="663"/>
    <data id="2" xNorm="0.525987006496752" yNorm="0.435013262599469" t="673"/>
    <data id="2" xNorm="0.525987006496752" yNorm="0.435013262599469" t="763"/>
  </datas>
</export>
